smsactivate/__init__.py
smsactivate/api.py
smsactivate_unofficial-1.3.dist-info/METADATA
smsactivate_unofficial-1.3.dist-info/WHEEL
smsactivate_unofficial-1.3.dist-info/top_level.txt
smsactivate_unofficial-1.3.dist-info/RECORD
